pytest_base_url/__init__.py
pytest_base_url/plugin.py
pytest_base_url-1.4.1.dist-info/DESCRIPTION.rst
pytest_base_url-1.4.1.dist-info/METADATA
pytest_base_url-1.4.1.dist-info/RECORD
pytest_base_url-1.4.1.dist-info/WHEEL
pytest_base_url-1.4.1.dist-info/entry_points.txt
pytest_base_url-1.4.1.dist-info/metadata.json
pytest_base_url-1.4.1.dist-info/top_level.txt
