Metadata-Version: 1.1
Name: pytest-base-url
Version: 1.4.1
Summary: pytest plugin for URL based testing
Home-page: https://github.com/pytest-dev/pytest-base-url
Author: Dave Hunt
Author-email: dhunt@mozilla.com
License: Mozilla Public License 2.0 (MPL 2.0)
Keywords: py.test pytest base url mozilla automation
Platform: UNKNOWN
Classifier: Development Status :: 5 - Production/Stable
Classifier: Framework :: Pytest
Classifier: Intended Audience :: Developers
Classifier: License :: OSI Approved :: Mozilla Public License 2.0 (MPL 2.0)
Classifier: Operating System :: POSIX
Classifier: Operating System :: Microsoft :: Windows
Classifier: Operating System :: MacOS :: MacOS X
Classifier: Topic :: Software Development :: Quality Assurance
Classifier: Topic :: Software Development :: Testing
Classifier: Topic :: Utilities
Classifier: Programming Language :: Python
Classifier: Programming Language :: Python :: 2.7
Classifier: Programming Language :: Python :: 3.6
Classifier: Programming Language :: Python :: Implementation :: CPython
Classifier: Programming Language :: Python :: Implementation :: PyPy
